README.md
setup.py
strip_deco/__init__.py
strip_deco.egg-info/PKG-INFO
strip_deco.egg-info/SOURCES.txt
strip_deco.egg-info/dependency_links.txt
strip_deco.egg-info/top_level.txt
tests/__init__.py
tests/conftest.py
tests/test_class_decorator.py
tests/test_class_method.py
tests/test_function_decorator.py
tests/test_mixed_decorator.py