Metadata-Version: 2.1
Name: strip-deco
Version: 0.0.9
Summary: Easily strip decorator from function or class method
Home-page: https://github.com/teamhide/strip-deco
Author: Hide
Author-email: padocon@naver.com
License: UNKNOWN
Platform: UNKNOWN
Classifier: Intended Audience :: Developers
Classifier: Programming Language :: Python
Classifier: Programming Language :: Python :: 3.4
Classifier: Programming Language :: Python :: 3.5
Classifier: Programming Language :: Python :: 3.6
Classifier: Programming Language :: Python :: 3.7
Classifier: Programming Language :: Python :: 3.8
Classifier: License :: OSI Approved :: Apache Software License
Classifier: Operating System :: OS Independent
Requires-Python: >=3.4
